fowopy/__init__.py
fowopy/fowo_client.py
fowopy/fowo_config.py
fowopy/schemas/__init__.py
fowopy/schemas/schemas.py
fowopy-0.0.2.dist-info/licenses/LICENSE
fowopy-0.0.2.dist-info/METADATA
fowopy-0.0.2.dist-info/WHEEL
fowopy-0.0.2.dist-info/top_level.txt
fowopy-0.0.2.dist-info/RECORD
