Metadata-Version: 2.4
Name: fowopy
Version: 0.0.2
Summary: Python SDK for interacting with the Football World (FOWO) API
Author-email: Narvik Aghamalian <narvik4it@gmail.com>
License: MIT
Project-URL: Homepage, https://github.com/ideavision/fowo
Project-URL: Bug Tracker, https://github.com/ideavision/fowo/issues
Project-URL: Documentation, https://github.com/ideavision/fowo/blob/master/sdk/README.md
Classifier: Programming Language :: Python :: 3.10
Classifier: Programming Language :: Python :: 3.11
Classifier: License :: OSI Approved :: MIT License
Classifier: Operating System :: OS Independent
Classifier: Development Status :: 3 - Alpha
Classifier: Intended Audience :: Developers
Classifier: Topic :: Software Development :: Libraries :: Python Modules
Classifier: Topic :: Software Development :: Libraries
Requires-Python: >=3.10
License-File: LICENSE
Requires-Dist: httpx>=0.27.0
Requires-Dist: pydantic>=2.4.0
Requires-Dist: backoff>=2.2.1
Requires-Dist: pyarrow>=16.0
Requires-Dist: python-dotenv>=1.0.0
Provides-Extra: dev
Requires-Dist: pytest>=8.1; extra == "dev"
Requires-Dist: pandas>=2.0.0; extra == "dev"
Dynamic: license-file
